LICENSE
MANIFEST.in
README.md
setup.cfg
setup.py
versioneer.py
.eggs/cython-3.1.2-py3.13-linux-x86_64.egg/Cython/Compiler/Code.pxd
.eggs/cython-3.1.2-py3.13-linux-x86_64.egg/Cython/Compiler/FlowControl.pxd
.eggs/cython-3.1.2-py3.13-linux-x86_64.egg/Cython/Compiler/ParseTreeTransforms.pxd
.eggs/cython-3.1.2-py3.13-linux-x86_64.egg/Cython/Compiler/Parsing.pxd
.eggs/cython-3.1.2-py3.13-linux-x86_64.egg/Cython/Compiler/Scanning.pxd
.eggs/cython-3.1.2-py3.13-linux-x86_64.egg/Cython/Compiler/Visitor.pxd
.eggs/cython-3.1.2-py3.13-linux-x86_64.egg/Cython/Includes/openmp.pxd
.eggs/cython-3.1.2-py3.13-linux-x86_64.egg/Cython/Includes/cpython/__init__.pxd
.eggs/cython-3.1.2-py3.13-linux-x86_64.egg/Cython/Includes/cpython/array.pxd
.eggs/cython-3.1.2-py3.13-linux-x86_64.egg/Cython/Includes/cpython/bool.pxd
.eggs/cython-3.1.2-py3.13-linux-x86_64.egg/Cython/Includes/cpython/buffer.pxd
.eggs/cython-3.1.2-py3.13-linux-x86_64.egg/Cython/Includes/cpython/bytearray.pxd
.eggs/cython-3.1.2-py3.13-linux-x86_64.egg/Cython/Includes/cpython/bytes.pxd
.eggs/cython-3.1.2-py3.13-linux-x86_64.egg/Cython/Includes/cpython/cellobject.pxd
.eggs/cython-3.1.2-py3.13-linux-x86_64.egg/Cython/Includes/cpython/ceval.pxd
.eggs/cython-3.1.2-py3.13-linux-x86_64.egg/Cython/Includes/cpython/codecs.pxd
.eggs/cython-3.1.2-py3.13-linux-x86_64.egg/Cython/Includes/cpython/complex.pxd
.eggs/cython-3.1.2-py3.13-linux-x86_64.egg/Cython/Includes/cpython/contextvars.pxd
.eggs/cython-3.1.2-py3.13-linux-x86_64.egg/Cython/Includes/cpython/conversion.pxd
.eggs/cython-3.1.2-py3.13-linux-x86_64.egg/Cython/Includes/cpython/datetime.pxd
.eggs/cython-3.1.2-py3.13-linux-x86_64.egg/Cython/Includes/cpython/descr.pxd
.eggs/cython-3.1.2-py3.13-linux-x86_64.egg/Cython/Includes/cpython/dict.pxd
.eggs/cython-3.1.2-py3.13-linux-x86_64.egg/Cython/Includes/cpython/exc.pxd
.eggs/cython-3.1.2-py3.13-linux-x86_64.egg/Cython/Includes/cpython/fileobject.pxd
.eggs/cython-3.1.2-py3.13-linux-x86_64.egg/Cython/Includes/cpython/float.pxd
pyrevolve.egg-info/PKG-INFO
pyrevolve.egg-info/SOURCES.txt
pyrevolve.egg-info/dependency_links.txt
pyrevolve.egg-info/not-zip-safe
pyrevolve.egg-info/requires.txt
pyrevolve.egg-info/top_level.txt
