Metadata-Version: 2.4
Name: pyrevolve
Version: 2.2.5
Summary: Python wrapper for Revolve checkpointing
Home-page: https://github.com/opesci/pyrevolve/
Author: Imperial College London
Author-email: g.gorman@imperial.ac.uk
License: MIT
Classifier: Programming Language :: Python :: 3
Classifier: Programming Language :: Python :: 3 :: Only
Classifier: Programming Language :: Python :: 3.10
Classifier: Programming Language :: Python :: 3.11
Classifier: Programming Language :: Python :: 3.12
Classifier: Programming Language :: Python :: 3.13
Requires-Python: >=3.10,<3.14
License-File: LICENSE
Requires-Dist: contexttimer
Requires-Dist: numpy
Provides-Extra: compression
Requires-Dist: blosc2; extra == "compression"
Requires-Dist: pyzfp; extra == "compression"
Dynamic: author
Dynamic: author-email
Dynamic: classifier
Dynamic: description
Dynamic: description-content-type
Dynamic: home-page
Dynamic: license
Dynamic: license-file
Dynamic: provides-extra
Dynamic: requires-dist
Dynamic: requires-python
Dynamic: summary
